{
    "type": [
      "null",
      "object"
    ],
    "properties": {
      "id": {
        "type": [
          "null",
          "string"
        ]
      },
      "benefitGroupPlanId": {
        "type": [
          "null",
          "string"
        ]
      },
      "benefitPlanCoverageId": {
        "type": [
          "null",
          "string"
        ]
      },
      "employeeCost": {
        "type": [
          "null",
          "string"
        ]
      },
      "companyCost": {
        "type": [
          "null",
          "string"
        ]
      },
      "startDate": {
        "type": [
          "null",
          "string"
        ]
      },
      "endDate": {
        "type": [
          "null",
          "string"
        ]
      },
      "archived": {
        "type": [
          "null",
          "boolean"
        ]
      }
    }
  }
  